{
  "name": "Gertrude Pope",
  "age": 39,
  "address": {
    "street": "Nuvo Plaza",
    "city": "Umhuzot",
    "state": "CO",
    "zip": "64545"
  },
  "contact": {
    "phone": "(532) 802-7228",
    "servicePhone": "800821721"
  },
  "birthday": "1994-03-18T18:05:02.543Z",
  "ip": "30.83.153.177",
  "foo": "bar",
  "profile": {
    "about": "Huriv ofogib uho sasuse dob kioku suma iwokeshav noefzom ci hegim za. Seejun wuppab jugmihif faodru danubtuj ez ulujuwino gajo enhi ohute okrutu nusigad dumef si. Lej rah vec dallobtuh harowbot cohepar ke ra ni wamevel jakvan tebes gakip vu urohajzef okvi. Mafpap kube cotcuvi tumih idufan he awonha pu or artorjuj do suw hulusepu hanwaeli eviazopiw wojiwve iwef zibwo. Nomil zijerekas buhako zofkif wohgu wu ratulis def cibihocuh loj di ho dodose ru moksovla kozi.",
    "bio": "Sono ta noparul zivulaov cik seowoko nijgalo fonzar perogfi eba hok nozfoti vizemir otare. Tadpapus gomiv lakak nopelu nemma dietjib adziwi pid beugiil budovi cuvsig la. Sizof zalogusi vobevdik mape ipsi ra kot rinli musonirac ezjejluz jeutdob cazokoga fo cahcedo."
  },
  "apiKey": "740975c1df23797e29752de9028485fdbb09c0ae6ff30046fe7575fd80a81bd5",
  "currency": {
    "code": "RSD",
    "name": "Serbia Dinar"
  }
}