{
  "name": "Helen Goodman",
  "age": 62,
  "address": {
    "street": "Ajmig Circle",
    "city": "Ezmila",
    "state": "MO",
    "zip": "78523"
  },
  "contact": {
    "phone": "(501) 400-3130",
    "servicePhone": "800441612"
  },
  "birthday": "1995-07-02T16:01:34.365Z",
  "ip": "221.51.8.153",
  "foo": "bar",
  "profile": {
    "about": "Simcuwmu niuzooh ukilev saembev ezi je cicap siw me ugkobes gah zahuj ho so bicokuw. Je emuejoje izhut gikele zulhi nerif betciz hoco sobuw neipo zasakjop kazhifdu. Du sojow fel cuconza niokaos orarupi va wu boj si isjo peikoor pucak bulvat olanelca. Laomre horkithom hepco liwke mi keuvdig jivudo wim ap bondob fokmew mi mi hi ecmegel uriguan sakfage ufweuvu. Icotuwsa izunew tiz di jivfun sehdotuhi hicgomcum wil vokzihek leparu tugi nowpu ado nu vev. Ezeevriz vafka aza lohu ap giv lav iwuajuce koobuj habi nuw caf.",
    "bio": "Mak efago sani rijhu aj ramzos bug sawhizica dizbawad mipolloj jomgage cege. Bavuh oma gitdon gofseazi incu wije pihno labofkop fujfiow eledif bavpub luictub. Cuvdenot wife pug wiwuwjaj fi jesezu reffati gok bim lu wokfo cabe me zosotwu. Fowa huwig bal keszovso cunupwu ofigimjok uhobup uc alucuzu impalavi bor movjapig tos. Cimhi eh toes palijo mazpa turleze li zikbaf wiwegu pizwah ratkop uwgefrir juztazlaw gignati ogbaz kivpilsi je."
  },
  "apiKey": "daca12aec3b74202d3cf3802ba1c87cd7b4064b7403ecd773296b6ecc30b5f75",
  "currency": {
    "code": "HTG",
    "name": "Haiti Gourde"
  }
}