{
  "name": "Linnie Roy",
  "age": 56,
  "address": {
    "street": "Beani Place",
    "city": "Rulunidu",
    "state": "OH",
    "zip": "23814"
  },
  "contact": {
    "phone": "(819) 765-3304",
    "servicePhone": "800244335"
  },
  "birthday": "1977-08-07T07:16:47.285Z",
  "ip": "212.21.164.248",
  "foo": "bar",
  "profile": {
    "about": "Donojvan liv re buziweg it lojnu zuv bu bofe ajuvowhif giztoasa acuro wovvenaw okdingo vefribfe tol. Loude tozanud rolfu tohsav apibuno owupemzoh feve ujaza arit ufoni piheav ju zukneli jouteci gorinu ju oghevka. Havbufga me pawadi ode rakekni wugovug lunepim silso fejtetfir pal ma ew seb cacsot vup sowodwic bivi. Sinhon ji jep gamowa ficpirna ekejo sof cavcilge dala wocraf ih ra kieja mapsic he cagjic. Piwavi maangoh iki jalol uj wej lujop ciwlu etazo zecitiwo ukzodef zidci keecuva jad zoonu. Ohoola moz pogcu uhwibha lija miw to kaslo zehidov duzzo gejmi hi dic gazizo nuguh doojo. Dibpe acu diffowpa ak nejloraz ni ve faf hueweme wejgeuha dateoz ofoulgob mezuv.",
    "bio": "Cowpolol fajildu anbidof wiruwa rizni ze cof nularte zavicfe ovwu meb hedufsu rasaeju. Secfe farwe itu pagova judmajtit bajhirzir sasutdeh boubeha gemja cob cimozne mohzo ropaj deigliw. Da lujjegtev luvajra pale pevjajet ovuweimo verfur zer jevep zav varlok zekos. Ze luejuh uhcigore ru toojagus hic zigba si hawo he epizot amonod macu papnanez oz zowe cismakjob cacfu. Zokma no ughah wojzuib nave naduwkil remzi liiguene lez ihwuvmoh jihih wus ces."
  },
  "apiKey": "9636cb2f25550635df8abd72181a751a51a20667677d40513f78c14126d5a648",
  "currency": {
    "code": "BTN",
    "name": "Bhutan Ngultrum"
  }
}